MANIFEST.in
readme.rst
requirements.txt
setup.py
jirafs_pandoc/__init__.py
jirafs_pandoc/pdf_template.tex
jirafs_pandoc/plugin.py
jirafs_pandoc.egg-info/PKG-INFO
jirafs_pandoc.egg-info/SOURCES.txt
jirafs_pandoc.egg-info/dependency_links.txt
jirafs_pandoc.egg-info/entry_points.txt
jirafs_pandoc.egg-info/requires.txt
jirafs_pandoc.egg-info/top_level.txt