Metadata-Version: 1.1
Name: jirafs-pandoc
Version: 1.2
Summary: Automatically convert markup supported by pandoc into PDF/HTML when uploading to JIRA.
Home-page: https://github.com/coddingtonbear/jirafs-pandoc
Author: Adam Coddington
Author-email: me@adamcoddington.net
License: UNKNOWN
Platform: UNKNOWN
Classifier: License :: OSI Approved :: MIT License
Classifier: Operating System :: OS Independent
Classifier: Programming Language :: Python :: 3
